colors_format/__init__.py
colors_format-1.1.2.dist-info/WHEEL
colors_format-1.1.2.dist-info/METADATA
colors_format-1.1.2.dist-info/RECORD
