Metadata-Version: 2.1
Name: colors-format
Version: 1.1.2
Summary: Tired of having to type up ANSI escape codes whenever you want to color some text, then use this package. It provides most 3-4 bit colors.
Author: Stefan Dikov
Author-email: stefan.v.dikov@gmail.com
Requires-Python: >=3.8,<4.0
Classifier: Programming Language :: Python :: 3
Classifier: Programming Language :: Python :: 3.10
Classifier: Programming Language :: Python :: 3.8
Classifier: Programming Language :: Python :: 3.9
